pallets_sphinx_themes/__init__.py
pallets_sphinx_themes/theme_check.py
pallets_sphinx_themes/themes/__init__.py
pallets_sphinx_themes/themes/click/__init__.py
pallets_sphinx_themes/themes/click/domain.py
pallets_sphinx_themes/themes/click/theme.conf
pallets_sphinx_themes/themes/click/static/click.css
pallets_sphinx_themes/themes/flask/theme.conf
pallets_sphinx_themes/themes/flask/static/flask.css
pallets_sphinx_themes/themes/jinja/__init__.py
pallets_sphinx_themes/themes/jinja/domain.py
pallets_sphinx_themes/themes/jinja/theme.conf
pallets_sphinx_themes/themes/jinja/static/jinja.css
pallets_sphinx_themes/themes/pocoo/__init__.py
pallets_sphinx_themes/themes/pocoo/ethicalads.html
pallets_sphinx_themes/themes/pocoo/layout.html
pallets_sphinx_themes/themes/pocoo/localtoc.html
pallets_sphinx_themes/themes/pocoo/project.html
pallets_sphinx_themes/themes/pocoo/relations.html
pallets_sphinx_themes/themes/pocoo/theme.conf
pallets_sphinx_themes/themes/pocoo/static/describe_version.js
pallets_sphinx_themes/themes/pocoo/static/pocoo.css
pallets_sphinx_themes/themes/werkzeug/theme.conf
pallets_sphinx_themes/themes/werkzeug/static/werkzeug.css
pallets_sphinx_themes-2.2.0.dist-info/entry_points.txt
pallets_sphinx_themes-2.2.0.dist-info/LICENSE.txt
pallets_sphinx_themes-2.2.0.dist-info/WHEEL
pallets_sphinx_themes-2.2.0.dist-info/METADATA
pallets_sphinx_themes-2.2.0.dist-info/RECORD
