Metadata-Version: 2.1
Name: Pallets-Sphinx-Themes
Version: 2.2.0
Summary: Sphinx themes for Pallets and related projects.
Maintainer-email: Pallets <contact@palletsprojects.com>
Requires-Python: >=3.8
Classifier: Development Status :: 5 - Production/Stable
Classifier: Framework :: Sphinx
Classifier: Framework :: Sphinx :: Theme
Classifier: Intended Audience :: Developers
Classifier: License :: OSI Approved :: BSD License
Classifier: Operating System :: OS Independent
Classifier: Programming Language :: Python
Classifier: Topic :: Documentation
Classifier: Topic :: Documentation :: Sphinx
Classifier: Topic :: Software Development :: Documentation
Requires-Dist: packaging
Requires-Dist: sphinx>=3
Requires-Dist: sphinx-notfound-page
Project-URL: Chat, https://discord.gg/pallets
Project-URL: Donate, https://palletsprojects.com/donate
Project-URL: Source, https://github.com/pallets/pallets-sphinx-themes/
